<?xml version="1.0"?>
<root>
<row FIELD1="459" age="63" sex="0" cp="0" trestbps="108" chol="269" fbs="0" restecg="1" thalach="169" exang="1" oldpeak="1.8" slope="1" ca="2" thal="2" target="0"></row>
<row FIELD1="460" age="58" sex="1" cp="2" trestbps="140" chol="211" fbs="1" restecg="0" thalach="165" exang="0" oldpeak="0.0" slope="2" ca="0" thal="2" target="1"></row>
<row FIELD1="461" age="51" sex="1" cp="0" trestbps="140" chol="298" fbs="0" restecg="1" thalach="122" exang="1" oldpeak="4.2" slope="1" ca="3" thal="3" target="0"></row>
<row FIELD1="462" age="68" sex="1" cp="2" trestbps="118" chol="277" fbs="0" restecg="1" thalach="151" exang="0" oldpeak="1.0" slope="2" ca="1" thal="3" target="1"></row>
<row FIELD1="463" age="69" sex="1" cp="3" trestbps="160" chol="234" fbs="1" restecg="0" thalach="131" exang="0" oldpeak="0.1" slope="1" ca="1" thal="2" target="1"></row>
<row FIELD1="464" age="55" sex="1" cp="0" trestbps="132" chol="353" fbs="0" restecg="1" thalach="132" exang="1" oldpeak="1.2" slope="1" ca="1" thal="3" target="0"></row>
<row FIELD1="465" age="45" sex="1" cp="0" trestbps="142" chol="309" fbs="0" restecg="0" thalach="147" exang="1" oldpeak="0.0" slope="1" ca="3" thal="3" target="0"></row>
<row FIELD1="466" age="77" sex="1" cp="0" trestbps="125" chol="304" fbs="0" restecg="0" thalach="162" exang="1" oldpeak="0.0" slope="2" ca="3" thal="2" target="0"></row>
<row FIELD1="467" age="66" sex="1" cp="0" trestbps="112" chol="212" fbs="0" restecg="0" thalach="132" exang="1" oldpeak="0.1" slope="2" ca="1" thal="2" target="0"></row>
<row FIELD1="468" age="58" sex="1" cp="2" trestbps="112" chol="230" fbs="0" restecg="0" thalach="165" exang="0" oldpeak="2.5" slope="1" ca="1" thal="3" target="0"></row>
<row FIELD1="469" age="51" sex="1" cp="2" trestbps="94" chol="227" fbs="0" restecg="1" thalach="154" exang="1" oldpeak="0.0" slope="2" ca="1" thal="3" target="1"></row>
<row FIELD1="470" age="49" sex="0" cp="0" trestbps="130" chol="269" fbs="0" restecg="1" thalach="163" exang="0" oldpeak="0.0" slope="2" ca="0" thal="2" target="1"></row>
<row FIELD1="471" age="59" sex="1" cp="2" trestbps="150" chol="212" fbs="1" restecg="1" thalach="157" exang="0" oldpeak="1.6" slope="2" ca="0" thal="2" target="1"></row>
<row FIELD1="472" age="56" sex="1" cp="1" trestbps="130" chol="221" fbs="0" restecg="0" thalach="163" exang="0" oldpeak="0.0" slope="2" ca="0" thal="3" target="1"></row>
<row FIELD1="473" age="69" sex="0" cp="3" trestbps="140" chol="239" fbs="0" restecg="1" thalach="151" exang="0" oldpeak="1.8" slope="2" ca="2" thal="2" target="1"></row>
<row FIELD1="474" age="50" sex="0" cp="2" trestbps="120" chol="219" fbs="0" restecg="1" thalach="158" exang="0" oldpeak="1.6" slope="1" ca="0" thal="2" target="1"></row>
<row FIELD1="475" age="61" sex="1" cp="3" trestbps="134" chol="234" fbs="0" restecg="1" thalach="145" exang="0" oldpeak="2.6" slope="1" ca="2" thal="2" target="0"></row>
<row FIELD1="476" age="56" sex="1" cp="0" trestbps="125" chol="249" fbs="1" restecg="0" thalach="144" exang="1" oldpeak="1.2" slope="1" ca="1" thal="2" target="0"></row>
<row FIELD1="477" age="51" sex="1" cp="0" trestbps="140" chol="299" fbs="0" restecg="1" thalach="173" exang="1" oldpeak="1.6" slope="2" ca="0" thal="3" target="0"></row>
<row FIELD1="478" age="51" sex="0" cp="2" trestbps="140" chol="308" fbs="0" restecg="0" thalach="142" exang="0" oldpeak="1.5" slope="2" ca="1" thal="2" target="1"></row>
<row FIELD1="479" age="43" sex="1" cp="0" trestbps="150" chol="247" fbs="0" restecg="1" thalach="171" exang="0" oldpeak="1.5" slope="2" ca="0" thal="2" target="1"></row>
<row FIELD1="480" age="70" sex="1" cp="0" trestbps="145" chol="174" fbs="0" restecg="1" thalach="125" exang="1" oldpeak="2.6" slope="0" ca="0" thal="3" target="0"></row>
<row FIELD1="481" age="55" sex="0" cp="1" trestbps="135" chol="250" fbs="0" restecg="0" thalach="161" exang="0" oldpeak="1.4" slope="1" ca="0" thal="2" target="1"></row>
<row FIELD1="482" age="58" sex="1" cp="0" trestbps="128" chol="259" fbs="0" restecg="0" thalach="130" exang="1" oldpeak="3.0" slope="1" ca="2" thal="3" target="0"></row>
<row FIELD1="483" age="53" sex="0" cp="2" trestbps="128" chol="216" fbs="0" restecg="0" thalach="115" exang="0" oldpeak="0.0" slope="2" ca="0" thal="0" target="1"></row>
<row FIELD1="484" age="51" sex="0" cp="0" trestbps="130" chol="305" fbs="0" restecg="1" thalach="142" exang="1" oldpeak="1.2" slope="1" ca="0" thal="3" target="0"></row>
<row FIELD1="485" age="54" sex="1" cp="0" trestbps="140" chol="239" fbs="0" restecg="1" thalach="160" exang="0" oldpeak="1.2" slope="2" ca="0" thal="2" target="1"></row>
<row FIELD1="486" age="63" sex="0" cp="0" trestbps="150" chol="407" fbs="0" restecg="0" thalach="154" exang="0" oldpeak="4.0" slope="1" ca="3" thal="3" target="0"></row>
<row FIELD1="487" age="56" sex="1" cp="2" trestbps="130" chol="256" fbs="1" restecg="0" thalach="142" exang="1" oldpeak="0.6" slope="1" ca="1" thal="1" target="0"></row>
<row FIELD1="488" age="57" sex="1" cp="0" trestbps="150" chol="276" fbs="0" restecg="0" thalach="112" exang="1" oldpeak="0.6" slope="1" ca="1" thal="1" target="0"></row>
<row FIELD1="489" age="44" sex="1" cp="0" trestbps="120" chol="169" fbs="0" restecg="1" thalach="144" exang="1" oldpeak="2.8" slope="0" ca="0" thal="1" target="0"></row>
<row FIELD1="490" age="37" sex="1" cp="2" trestbps="130" chol="250" fbs="0" restecg="1" thalach="187" exang="0" oldpeak="3.5" slope="0" ca="0" thal="2" target="1"></row>
<row FIELD1="491" age="38" sex="1" cp="2" trestbps="138" chol="175" fbs="0" restecg="1" thalach="173" exang="0" oldpeak="0.0" slope="2" ca="4" thal="2" target="1"></row>
<row FIELD1="492" age="59" sex="1" cp="3" trestbps="170" chol="288" fbs="0" restecg="0" thalach="159" exang="0" oldpeak="0.2" slope="1" ca="0" thal="3" target="0"></row>
<row FIELD1="493" age="59" sex="1" cp="3" trestbps="170" chol="288" fbs="0" restecg="0" thalach="159" exang="0" oldpeak="0.2" slope="1" ca="0" thal="3" target="0"></row>
<row FIELD1="494" age="39" sex="0" cp="2" trestbps="138" chol="220" fbs="0" restecg="1" thalach="152" exang="0" oldpeak="0.0" slope="1" ca="0" thal="2" target="1"></row>
<row FIELD1="495" age="59" sex="1" cp="3" trestbps="170" chol="288" fbs="0" restecg="0" thalach="159" exang="0" oldpeak="0.2" slope="1" ca="0" thal="3" target="0"></row>
<row FIELD1="496" age="47" sex="1" cp="0" trestbps="112" chol="204" fbs="0" restecg="1" thalach="143" exang="0" oldpeak="0.1" slope="2" ca="0" thal="2" target="1"></row>
<row FIELD1="497" age="52" sex="1" cp="0" trestbps="108" chol="233" fbs="1" restecg="1" thalach="147" exang="0" oldpeak="0.1" slope="2" ca="3" thal="3" target="1"></row>
<row FIELD1="498" age="60" sex="1" cp="0" trestbps="117" chol="230" fbs="1" restecg="1" thalach="160" exang="1" oldpeak="1.4" slope="2" ca="2" thal="3" target="0"></row>
<row FIELD1="499" age="51" sex="1" cp="2" trestbps="100" chol="222" fbs="0" restecg="1" thalach="143" exang="1" oldpeak="1.2" slope="1" ca="0" thal="2" target="1"></row>
<row FIELD1="500" age="38" sex="1" cp="3" trestbps="120" chol="231" fbs="0" restecg="1" thalach="182" exang="1" oldpeak="3.8" slope="1" ca="0" thal="3" target="0"></row>
<row FIELD1="501" age="57" sex="1" cp="0" trestbps="110" chol="335" fbs="0" restecg="1" thalach="143" exang="1" oldpeak="3.0" slope="1" ca="1" thal="3" target="0"></row>
<row FIELD1="502" age="45" sex="1" cp="0" trestbps="142" chol="309" fbs="0" restecg="0" thalach="147" exang="1" oldpeak="0.0" slope="1" ca="3" thal="3" target="0"></row>
<row FIELD1="503" age="59" sex="1" cp="0" trestbps="140" chol="177" fbs="0" restecg="1" thalach="162" exang="1" oldpeak="0.0" slope="2" ca="1" thal="3" target="0"></row>
<row FIELD1="504" age="67" sex="1" cp="0" trestbps="160" chol="286" fbs="0" restecg="0" thalach="108" exang="1" oldpeak="1.5" slope="1" ca="3" thal="2" target="0"></row>
<row FIELD1="505" age="62" sex="0" cp="0" trestbps="160" chol="164" fbs="0" restecg="0" thalach="145" exang="0" oldpeak="6.2" slope="0" ca="3" thal="3" target="0"></row>
<row FIELD1="506" age="44" sex="1" cp="1" trestbps="120" chol="220" fbs="0" restecg="1" thalach="170" exang="0" oldpeak="0.0" slope="2" ca="0" thal="2" target="1"></row>
<row FIELD1="507" age="55" sex="0" cp="0" trestbps="180" chol="327" fbs="0" restecg="2" thalach="117" exang="1" oldpeak="3.4" slope="1" ca="0" thal="2" target="0"></row>
<row FIELD1="508" age="38" sex="1" cp="2" trestbps="138" chol="175" fbs="0" restecg="1" thalach="173" exang="0" oldpeak="0.0" slope="2" ca="4" thal="2" target="1"></row>
<row FIELD1="509" age="63" sex="1" cp="0" trestbps="130" chol="254" fbs="0" restecg="0" thalach="147" exang="0" oldpeak="1.4" slope="1" ca="1" thal="3" target="0"></row>
</root>